{
  "openapi": "3.0.0",
  "info": {
    "title": "2025-1 Cap",
    "version": "1.0.0",
    "description": "캡스톤 프로젝트 API 문서입니다."
  },
  "servers": [
    {
      "url": "http://localhost:3000",
      "description": "API Server"
    },
    {
      "url": "https://thiscatthatcat.shop",
      "description": "Production Domain"
    },
    {
      "url": "https://13.209.12.236:3000",
      "description": "Public IP Server"
    }
  ],
  "paths": {
    "/": {
      "get": {
        "description": "",
        "responses": {
          "200": {
            "description": "OK"
          }
        }
      }
    },
    "/users/signup": {
      "post": {
        "tags": [
          "User"
        ],
        "summary": "회원 가입 API",
        "description": "",
        "responses": {
          "200": {
            "description": "회원 가입 성공 응답",
            "content": {
              "application/json": {
                "schema": {
                  "type": "object",
                  "properties": {
                    "isSuccess": {
                      "type": "boolean",
                      "example": true
                    },
                    "code": {
                      "type": "number",
                      "example": 200
                    },
                    "message": {
                      "type": "string",
                      "example": "회원 가입이 성공적으로 완료되었습니다."
                    },
                    "result": {
                      "type": "object",
                      "properties": {
                        "id": {
                          "type": "string",
                          "example": "1"
                        },
                        "nickname": {
                          "type": "string",
                          "example": "nickname"
                        },
                        "email": {
                          "type": "string",
                          "example": "user@example.com"
                        },
                        "point": {
                          "type": "number",
                          "example": 0
                        },
                        "ranking": {
                          "type": "object",
                          "properties": {
                            "rank": {
                              "type": "number",
                              "example": 1
                            },
                            "tier": {
                              "type": "string",
                              "example": "아이언"
                            }
                          }
                        }
                      }
                    }
                  }
                }
              }
            }
          },
          "400": {
            "description": "회원 가입 실패 응답 (필수 값 누락)",
            "content": {
              "application/json": {
                "schema": {
                  "type": "object",
                  "properties": {
                    "isSuccess": {
                      "type": "boolean",
                      "example": false
                    },
                    "code": {
                      "type": "string",
                      "example": "MEMBER_NOT_FOUND"
                    },
                    "message": {
                      "type": "string",
                      "example": "필수 항목이 누락되었습니다."
                    },
                    "result": {
                      "type": "object",
                      "nullable": true,
                      "example": null
                    }
                  }
                }
              }
            }
          },
          "401": {
            "description": "Unauthorized"
          },
          "403": {
            "description": "Forbidden"
          },
          "409": {
            "description": "회원 가입 실패 응답 (이메일 중복)",
            "content": {
              "application/json": {
                "schema": {
                  "type": "object",
                  "properties": {
                    "isSuccess": {
                      "type": "boolean",
                      "example": false
                    },
                    "code": {
                      "type": "string",
                      "example": "EMAIL_ALREADY_EXIST"
                    },
                    "message": {
                      "type": "string",
                      "example": "이미 사용 중인 이메일입니다."
                    },
                    "result": {
                      "type": "object",
                      "nullable": true,
                      "example": null
                    }
                  }
                }
              }
            }
          },
          "500": {
            "description": "Internal Server Error"
          }
        },
        "requestBody": {
          "required": true,
          "content": {
            "application/json": {
              "schema": {
                "type": "object",
                "required": [
                  "nickname",
                  "name",
                  "email",
                  "password",
                  "gender",
                  "birth",
                  "phoneNumber"
                ],
                "properties": {
                  "nickname": {
                    "type": "string",
                    "example": "nickname"
                  },
                  "name": {
                    "type": "string",
                    "example": "John Doe"
                  },
                  "email": {
                    "type": "string",
                    "example": "user@example.com"
                  },
                  "password": {
                    "type": "string",
                    "example": "password123"
                  },
                  "gender": {
                    "type": "string",
                    "example": "M"
                  },
                  "birth": {
                    "type": "string",
                    "format": "date",
                    "example": "1990-05-18"
                  },
                  "phoneNumber": {
                    "type": "string",
                    "example": "010-1234-5678"
                  }
                }
              }
            }
          }
        }
      }
    },
    "/users/login": {
      "post": {
        "tags": [
          "User"
        ],
        "summary": "로그인 API",
        "description": "",
        "responses": {
          "200": {
            "description": "로그인 성공 응답",
            "content": {
              "application/json": {
                "schema": {
                  "type": "object",
                  "properties": {
                    "isSuccess": {
                      "type": "boolean",
                      "example": true
                    },
                    "code": {
                      "type": "number",
                      "example": 200
                    },
                    "message": {
                      "type": "string",
                      "example": "로그인 성공"
                    },
                    "result": {
                      "type": "object",
                      "properties": {
                        "token": {
                          "type": "string",
                          "example": "jwt-token-string"
                        },
                        "user": {
                          "type": "object",
                          "properties": {
                            "id": {
                              "type": "string",
                              "example": "1"
                            },
                            "email": {
                              "type": "string",
                              "example": "user@example.com"
                            },
                            "status": {
                              "type": "string",
                              "example": "active"
                            }
                          }
                        }
                      }
                    }
                  }
                }
              }
            }
          },
          "400": {
            "description": "로그인 실패 (이메일 미존재)",
            "content": {
              "application/json": {
                "schema": {
                  "type": "object",
                  "properties": {
                    "isSuccess": {
                      "type": "boolean",
                      "example": false
                    },
                    "code": {
                      "type": "string",
                      "example": "LOGIN_ID_NOT_EXIST"
                    },
                    "message": {
                      "type": "string",
                      "example": "등록되지 않은 이메일입니다."
                    },
                    "result": {
                      "type": "object",
                      "nullable": true,
                      "example": null
                    }
                  }
                }
              }
            }
          },
          "401": {
            "description": "로그인 실패 (비밀번호 불일치)",
            "content": {
              "application/json": {
                "schema": {
                  "type": "object",
                  "properties": {
                    "isSuccess": {
                      "type": "boolean",
                      "example": false
                    },
                    "code": {
                      "type": "string",
                      "example": "LOGIN_PASSWORD_WRONG"
                    },
                    "message": {
                      "type": "string",
                      "example": "비밀번호가 일치하지 않습니다."
                    },
                    "result": {
                      "type": "object",
                      "nullable": true,
                      "example": null
                    }
                  }
                }
              }
            }
          },
          "403": {
            "description": "Forbidden"
          },
          "500": {
            "description": "Internal Server Error"
          }
        },
        "requestBody": {
          "required": true,
          "content": {
            "application/json": {
              "schema": {
                "type": "object",
                "properties": {
                  "email": {
                    "type": "string",
                    "example": "user@example.com"
                  },
                  "password": {
                    "type": "string",
                    "example": "password123"
                  }
                }
              }
            }
          }
        }
      }
    },
    "/users/info": {
      "get": {
        "tags": [
          "User"
        ],
        "summary": "유저 정보 불러오기 API",
        "description": "",
        "responses": {
          "200": {
            "description": "유저 정보 성공 응답",
            "content": {
              "application/json": {
                "schema": {
                  "type": "object",
                  "properties": {
                    "isSuccess": {
                      "type": "boolean",
                      "example": true
                    },
                    "code": {
                      "type": "number",
                      "example": 200
                    },
                    "message": {
                      "type": "string",
                      "example": "유저 정보 조회 성공"
                    },
                    "result": {
                      "type": "object",
                      "properties": {
                        "id": {
                          "type": "string",
                          "example": "1"
                        },
                        "email": {
                          "type": "string",
                          "example": "user@example.com"
                        },
                        "nickname": {
                          "type": "string",
                          "example": "nickname"
                        },
                        "name": {
                          "type": "string",
                          "example": "John Doe"
                        },
                        "status": {
                          "type": "string",
                          "example": "active"
                        },
                        "profileImageUrl": {
                          "type": "string",
                          "nullable": true,
                          "example": null
                        },
                        "createdAt": {
                          "type": "string",
                          "format": "date",
                          "example": "2021-05-12"
                        },
                        "updatedAt": {
                          "type": "string",
                          "format": "date",
                          "example": "2021-06-15"
                        }
                      }
                    }
                  }
                }
              }
            }
          },
          "400": {
            "description": "잘못된 토큰 포맷",
            "content": {
              "application/json": {
                "schema": {
                  "type": "object",
                  "properties": {
                    "isSuccess": {
                      "type": "boolean",
                      "example": false
                    },
                    "code": {
                      "type": "string",
                      "example": "TOKEN_FORMAT_INCORRECT"
                    },
                    "message": {
                      "type": "string",
                      "example": "토큰 포맷이 올바르지 않습니다."
                    },
                    "result": {
                      "type": "object",
                      "nullable": true,
                      "example": null
                    }
                  }
                }
              }
            }
          },
          "401": {
            "description": "Unauthorized"
          },
          "403": {
            "description": "Forbidden"
          },
          "500": {
            "description": "서버 오류",
            "content": {
              "application/json": {
                "schema": {
                  "type": "object",
                  "properties": {
                    "isSuccess": {
                      "type": "boolean",
                      "example": false
                    },
                    "code": {
                      "type": "string",
                      "example": "SERVER_ERROR"
                    },
                    "message": {
                      "type": "string",
                      "example": "서버 오류가 발생했습니다."
                    },
                    "result": {
                      "type": "object",
                      "nullable": true,
                      "example": null
                    }
                  }
                }
              }
            }
          }
        },
        "security": [
          {
            "BearerAuth": []
          }
        ]
      }
    },
    "/rankings/top": {
      "get": {
        "tags": [
          "Ranking"
        ],
        "summary": "Top 랭킹 리스트 조회 API",
        "description": "",
        "responses": {
          "200": {
            "description": "Top 랭킹 리스트 조회 성공",
            "content": {
              "application/json": {
                "schema": {
                  "type": "object",
                  "properties": {
                    "isSuccess": {
                      "type": "boolean",
                      "example": true
                    },
                    "code": {
                      "type": "number",
                      "example": 200
                    },
                    "message": {
                      "type": "string",
                      "example": "랭킹 리스트 조회 성공"
                    },
                    "result": {
                      "type": "array",
                      "items": {
                        "type": "object",
                        "properties": {
                          "userId": {
                            "type": "string",
                            "example": "1"
                          },
                          "nickname": {
                            "type": "string",
                            "example": "치멘"
                          },
                          "rank": {
                            "type": "number",
                            "example": 1
                          },
                          "previousRank": {
                            "type": "number",
                            "nullable": true,
                            "example": null
                          },
                          "tier": {
                            "type": "string",
                            "example": "브론즈"
                          },
                          "totalPoints": {
                            "type": "number",
                            "example": 1500
                          }
                        }
                      }
                    }
                  }
                }
              }
            }
          },
          "401": {
            "description": "Unauthorized"
          },
          "403": {
            "description": "Forbidden"
          },
          "500": {
            "description": "서버 오류",
            "content": {
              "application/json": {
                "schema": {
                  "type": "object",
                  "properties": {
                    "isSuccess": {
                      "type": "boolean",
                      "example": false
                    },
                    "code": {
                      "type": "string",
                      "example": "SERVER_ERROR"
                    },
                    "message": {
                      "type": "string",
                      "example": "서버 오류가 발생했습니다."
                    },
                    "result": {
                      "type": "object",
                      "nullable": true,
                      "example": null
                    }
                  }
                }
              }
            }
          }
        }
      }
    },
    "/battle/rooms": {
      "post": {
        "tags": [
          "BattleRoom"
        ],
        "summary": "배틀방 생성 API",
        "description": "",
        "responses": {
          "200": {
            "description": "배틀방 생성 성공",
            "content": {
              "application/json": {
                "schema": {
                  "type": "object",
                  "properties": {
                    "isSuccess": {
                      "type": "boolean",
                      "example": true
                    },
                    "code": {
                      "type": "number",
                      "example": 200
                    },
                    "message": {
                      "type": "string",
                      "example": "배틀방 생성 성공"
                    },
                    "result": {
                      "type": "object",
                      "properties": {
                        "roomId": {
                          "type": "number",
                          "example": 1
                        },
                        "adminId": {
                          "type": "number",
                          "example": 1
                        },
                        "topicA": {
                          "type": "string",
                          "example": "사자"
                        },
                        "topicB": {
                          "type": "string",
                          "example": "호랑이"
                        },
                        "status": {
                          "type": "string",
                          "example": "WAITING"
                        },
                        "createdAt": {
                          "type": "string",
                          "format": "date-time",
                          "example": "2025-05-25T12:34:56.000Z"
                        },
                        "topics": {
                          "type": "array",
                          "items": {
                            "type": "object",
                            "properties": {
                              "topicId": {
                                "type": "number",
                                "example": 1
                              },
                              "side": {
                                "type": "string",
                                "example": "A"
                              },
                              "title": {
                                "type": "string",
                                "example": "사자"
                              },
                              "suggestedBy": {
                                "type": "string",
                                "example": "user"
                              },
                              "createdAt": {
                                "type": "string",
                                "format": "date-time",
                                "example": "2025-05-25T12:34:56.000Z"
                              }
                            }
                          }
                        }
                      }
                    }
                  }
                }
              }
            }
          },
          "400": {
            "description": "잘못된 입력",
            "content": {
              "application/json": {
                "schema": {
                  "type": "object",
                  "properties": {
                    "isSuccess": {
                      "type": "boolean",
                      "example": false
                    },
                    "code": {
                      "type": "string",
                      "example": "INVALID_INPUT"
                    },
                    "message": {
                      "type": "string",
                      "example": "필수 입력값이 누락되었습니다."
                    },
                    "result": {
                      "type": "object",
                      "nullable": true,
                      "example": null
                    }
                  }
                }
              }
            }
          },
          "401": {
            "description": "토큰 오류",
            "content": {
              "application/json": {
                "schema": {
                  "type": "object",
                  "properties": {
                    "isSuccess": {
                      "type": "boolean",
                      "example": false
                    },
                    "code": {
                      "type": "string",
                      "example": "TOKEN_FORMAT_INCORRECT"
                    },
                    "message": {
                      "type": "string",
                      "example": "토큰 포맷이 올바르지 않습니다."
                    },
                    "result": {
                      "type": "object",
                      "nullable": true,
                      "example": null
                    }
                  }
                }
              }
            }
          },
          "403": {
            "description": "Forbidden"
          },
          "500": {
            "description": "서버 오류",
            "content": {
              "application/json": {
                "schema": {
                  "type": "object",
                  "properties": {
                    "isSuccess": {
                      "type": "boolean",
                      "example": false
                    },
                    "code": {
                      "type": "string",
                      "example": "SERVER_ERROR"
                    },
                    "message": {
                      "type": "string",
                      "example": "서버 오류가 발생했습니다."
                    },
                    "result": {
                      "type": "object",
                      "nullable": true,
                      "example": null
                    }
                  }
                }
              }
            }
          }
        },
        "security": [
          {
            "BearerAuth": []
          }
        ],
        "requestBody": {
          "required": true,
          "content": {
            "application/json": {
              "schema": {
                "type": "object",
                "properties": {
                  "topics": {
                    "type": "array",
                    "items": {
                      "type": "object",
                      "properties": {
                        "side": {
                          "type": "string",
                          "example": "A"
                        },
                        "title": {
                          "type": "string",
                          "example": "사자"
                        },
                        "suggestedBy": {
                          "type": "string",
                          "example": "user"
                        }
                      },
                      "required": [
                        "side",
                        "title"
                      ]
                    },
                    "example": [
                      {
                        "side": "A",
                        "title": "사자",
                        "suggestedBy": "user"
                      },
                      {
                        "side": "B",
                        "title": "호랑이",
                        "suggestedBy": "user"
                      }
                    ]
                  }
                }
              }
            }
          }
        }
      }
    },
    "/battle/rooms/{roomId}": {
      "get": {
        "tags": [
          "BattleRoom"
        ],
        "summary": "방 정보 불러오는 API",
        "description": "",
        "parameters": [
          {
            "name": "roomId",
            "in": "path",
            "required": true,
            "schema": {
              "type": "string"
            },
            "description": "배틀방 ID",
            "format": "int64",
            "example": 1
          }
        ],
        "responses": {
          "200": {
            "description": "조회 성공",
            "content": {
              "application/json": {
                "schema": {
                  "type": "object",
                  "properties": {
                    "isSuccess": {
                      "type": "boolean",
                      "example": true
                    },
                    "code": {
                      "type": "string",
                      "example": "200"
                    },
                    "message": {
                      "type": "string",
                      "example": "success!"
                    },
                    "result": {
                      "type": "object",
                      "properties": {
                        "roomId": {
                          "type": "number",
                          "example": 1
                        },
                        "adminId": {
                          "type": "number",
                          "example": 5
                        },
                        "topicA": {
                          "type": "string",
                          "example": "사자"
                        },
                        "topicB": {
                          "type": "string",
                          "example": "코끼리"
                        },
                        "status": {
                          "type": "string",
                          "example": "WAITING"
                        },
                        "createdAt": {
                          "type": "string",
                          "example": "2025-05-25T12:00:00.000Z"
                        },
                        "participants": {
                          "type": "array",
                          "items": {
                            "type": "object",
                            "properties": {
                              "userId": {
                                "type": "number",
                                "example": 9
                              },
                              "role": {
                                "type": "string",
                                "example": "A"
                              },
                              "joinedAt": {
                                "type": "string",
                                "example": "2025-05-25T12:01:00.000Z"
                              }
                            }
                          }
                        },
                        "spectatorCount": {
                          "type": "number",
                          "example": 3
                        }
                      }
                    }
                  },
                  "xml": {
                    "name": "main"
                  }
                }
              },
              "application/xml": {
                "schema": {
                  "type": "object",
                  "properties": {
                    "isSuccess": {
                      "type": "boolean",
                      "example": true
                    },
                    "code": {
                      "type": "string",
                      "example": "200"
                    },
                    "message": {
                      "type": "string",
                      "example": "success!"
                    },
                    "result": {
                      "type": "object",
                      "properties": {
                        "roomId": {
                          "type": "number",
                          "example": 1
                        },
                        "adminId": {
                          "type": "number",
                          "example": 5
                        },
                        "topicA": {
                          "type": "string",
                          "example": "사자"
                        },
                        "topicB": {
                          "type": "string",
                          "example": "코끼리"
                        },
                        "status": {
                          "type": "string",
                          "example": "WAITING"
                        },
                        "createdAt": {
                          "type": "string",
                          "example": "2025-05-25T12:00:00.000Z"
                        },
                        "participants": {
                          "type": "array",
                          "items": {
                            "type": "object",
                            "properties": {
                              "userId": {
                                "type": "number",
                                "example": 9
                              },
                              "role": {
                                "type": "string",
                                "example": "A"
                              },
                              "joinedAt": {
                                "type": "string",
                                "example": "2025-05-25T12:01:00.000Z"
                              }
                            }
                          }
                        },
                        "spectatorCount": {
                          "type": "number",
                          "example": 3
                        }
                      }
                    }
                  },
                  "xml": {
                    "name": "main"
                  }
                }
              }
            }
          },
          "400": {
            "description": "잘못된 요청",
            "content": {
              "application/json": {
                "schema": {
                  "type": "object",
                  "properties": {
                    "isSuccess": {
                      "type": "boolean",
                      "example": false
                    },
                    "code": {
                      "type": "string",
                      "example": "COMMON001"
                    },
                    "message": {
                      "type": "string",
                      "example": "잘못된 요청입니다."
                    },
                    "result": {}
                  },
                  "xml": {
                    "name": "main"
                  }
                }
              },
              "application/xml": {
                "schema": {
                  "type": "object",
                  "properties": {
                    "isSuccess": {
                      "type": "boolean",
                      "example": false
                    },
                    "code": {
                      "type": "string",
                      "example": "COMMON001"
                    },
                    "message": {
                      "type": "string",
                      "example": "잘못된 요청입니다."
                    },
                    "result": {}
                  },
                  "xml": {
                    "name": "main"
                  }
                }
              }
            }
          },
          "401": {
            "description": "토큰 오류",
            "content": {
              "application/json": {
                "schema": {
                  "type": "object",
                  "properties": {
                    "isSuccess": {
                      "type": "boolean",
                      "example": false
                    },
                    "code": {
                      "type": "string",
                      "example": "MEMBER4006"
                    },
                    "message": {
                      "type": "string",
                      "example": "토큰의 형식이 올바르지 않습니다. 다시 확인해주세요."
                    },
                    "result": {}
                  },
                  "xml": {
                    "name": "main"
                  }
                }
              },
              "application/xml": {
                "schema": {
                  "type": "object",
                  "properties": {
                    "isSuccess": {
                      "type": "boolean",
                      "example": false
                    },
                    "code": {
                      "type": "string",
                      "example": "MEMBER4006"
                    },
                    "message": {
                      "type": "string",
                      "example": "토큰의 형식이 올바르지 않습니다. 다시 확인해주세요."
                    },
                    "result": {}
                  },
                  "xml": {
                    "name": "main"
                  }
                }
              }
            }
          },
          "403": {
            "description": "Forbidden"
          },
          "404": {
            "description": "방을 찾을 수 없음",
            "content": {
              "application/json": {
                "schema": {
                  "type": "object",
                  "properties": {
                    "isSuccess": {
                      "type": "boolean",
                      "example": false
                    },
                    "code": {
                      "type": "string",
                      "example": "ROOMIN4005"
                    },
                    "message": {
                      "type": "string",
                      "example": "방을 찾을 수가 없습니다."
                    },
                    "result": {}
                  },
                  "xml": {
                    "name": "main"
                  }
                }
              },
              "application/xml": {
                "schema": {
                  "type": "object",
                  "properties": {
                    "isSuccess": {
                      "type": "boolean",
                      "example": false
                    },
                    "code": {
                      "type": "string",
                      "example": "ROOMIN4005"
                    },
                    "message": {
                      "type": "string",
                      "example": "방을 찾을 수가 없습니다."
                    },
                    "result": {}
                  },
                  "xml": {
                    "name": "main"
                  }
                }
              }
            }
          },
          "500": {
            "description": "서버 내부 오류",
            "content": {
              "application/json": {
                "schema": {
                  "type": "object",
                  "properties": {
                    "isSuccess": {
                      "type": "boolean",
                      "example": false
                    },
                    "code": {
                      "type": "string",
                      "example": "COMMON000"
                    },
                    "message": {
                      "type": "string",
                      "example": "서버 에러, 관리자에게 문의 바랍니다."
                    },
                    "result": {}
                  },
                  "xml": {
                    "name": "main"
                  }
                }
              },
              "application/xml": {
                "schema": {
                  "type": "object",
                  "properties": {
                    "isSuccess": {
                      "type": "boolean",
                      "example": false
                    },
                    "code": {
                      "type": "string",
                      "example": "COMMON000"
                    },
                    "message": {
                      "type": "string",
                      "example": "서버 에러, 관리자에게 문의 바랍니다."
                    },
                    "result": {}
                  },
                  "xml": {
                    "name": "main"
                  }
                }
              }
            }
          }
        },
        "security": [
          {
            "BearerAuth": []
          }
        ]
      }
    },
    "/battle/rooms/{roomId}/participants": {
      "post": {
        "tags": [
          "BattleRoom"
        ],
        "summary": "방 참가 API",
        "description": "",
        "parameters": [
          {
            "name": "roomId",
            "in": "path",
            "required": true,
            "schema": {
              "type": "string"
            },
            "description": "배틀방 ID",
            "format": "int64",
            "example": 1
          }
        ],
        "responses": {
          "200": {
            "description": "참가 성공",
            "content": {
              "application/json": {
                "schema": {
                  "type": "object",
                  "properties": {
                    "isSuccess": {
                      "type": "boolean",
                      "example": true
                    },
                    "code": {
                      "type": "string",
                      "example": "200"
                    },
                    "message": {
                      "type": "string",
                      "example": "success!"
                    },
                    "result": {
                      "type": "object",
                      "properties": {
                        "participantId": {
                          "type": "number",
                          "example": 123
                        },
                        "roomId": {
                          "type": "number",
                          "example": 1
                        },
                        "userId": {
                          "type": "number",
                          "example": 42
                        },
                        "role": {
                          "type": "string",
                          "example": "A"
                        },
                        "joinedAt": {
                          "type": "string",
                          "example": "2025-05-25T10:48:19.983Z"
                        }
                      }
                    }
                  },
                  "xml": {
                    "name": "main"
                  }
                }
              },
              "application/xml": {
                "schema": {
                  "type": "object",
                  "properties": {
                    "isSuccess": {
                      "type": "boolean",
                      "example": true
                    },
                    "code": {
                      "type": "string",
                      "example": "200"
                    },
                    "message": {
                      "type": "string",
                      "example": "success!"
                    },
                    "result": {
                      "type": "object",
                      "properties": {
                        "participantId": {
                          "type": "number",
                          "example": 123
                        },
                        "roomId": {
                          "type": "number",
                          "example": 1
                        },
                        "userId": {
                          "type": "number",
                          "example": 42
                        },
                        "role": {
                          "type": "string",
                          "example": "A"
                        },
                        "joinedAt": {
                          "type": "string",
                          "example": "2025-05-25T10:48:19.983Z"
                        }
                      }
                    }
                  },
                  "xml": {
                    "name": "main"
                  }
                }
              }
            }
          },
          "400": {
            "description": "잘못된 요청",
            "content": {
              "application/json": {
                "schema": {
                  "type": "object",
                  "properties": {
                    "isSuccess": {
                      "type": "boolean",
                      "example": false
                    },
                    "code": {
                      "type": "string",
                      "example": "COMMON001"
                    },
                    "message": {
                      "type": "string",
                      "example": "잘못된 요청입니다."
                    },
                    "result": {}
                  },
                  "xml": {
                    "name": "main"
                  }
                }
              },
              "application/xml": {
                "schema": {
                  "type": "object",
                  "properties": {
                    "isSuccess": {
                      "type": "boolean",
                      "example": false
                    },
                    "code": {
                      "type": "string",
                      "example": "COMMON001"
                    },
                    "message": {
                      "type": "string",
                      "example": "잘못된 요청입니다."
                    },
                    "result": {}
                  },
                  "xml": {
                    "name": "main"
                  }
                }
              }
            }
          },
          "401": {
            "description": "토큰 오류",
            "content": {
              "application/json": {
                "schema": {
                  "type": "object",
                  "properties": {
                    "isSuccess": {
                      "type": "boolean",
                      "example": false
                    },
                    "code": {
                      "type": "string",
                      "example": "MEMBER4006"
                    },
                    "message": {
                      "type": "string",
                      "example": "토큰의 형식이 올바르지 않습니다. 다시 확인해주세요."
                    },
                    "result": {}
                  },
                  "xml": {
                    "name": "main"
                  }
                }
              },
              "application/xml": {
                "schema": {
                  "type": "object",
                  "properties": {
                    "isSuccess": {
                      "type": "boolean",
                      "example": false
                    },
                    "code": {
                      "type": "string",
                      "example": "MEMBER4006"
                    },
                    "message": {
                      "type": "string",
                      "example": "토큰의 형식이 올바르지 않습니다. 다시 확인해주세요."
                    },
                    "result": {}
                  },
                  "xml": {
                    "name": "main"
                  }
                }
              }
            }
          },
          "403": {
            "description": "Forbidden"
          },
          "409": {
            "description": "참가 불가",
            "content": {
              "application/json": {
                "schema": {
                  "type": "object",
                  "properties": {
                    "isSuccess": {
                      "type": "boolean",
                      "example": false
                    },
                    "code": {
                      "type": "string",
                      "example": "ROOMIN4005"
                    },
                    "message": {
                      "type": "string",
                      "example": "이미 참가했습니다."
                    },
                    "result": {}
                  },
                  "xml": {
                    "name": "main"
                  }
                }
              },
              "application/xml": {
                "schema": {
                  "type": "object",
                  "properties": {
                    "isSuccess": {
                      "type": "boolean",
                      "example": false
                    },
                    "code": {
                      "type": "string",
                      "example": "ROOMIN4005"
                    },
                    "message": {
                      "type": "string",
                      "example": "이미 참가했습니다."
                    },
                    "result": {}
                  },
                  "xml": {
                    "name": "main"
                  }
                }
              }
            }
          },
          "500": {
            "description": "서버 내부 오류",
            "content": {
              "application/json": {
                "schema": {
                  "type": "object",
                  "properties": {
                    "isSuccess": {
                      "type": "boolean",
                      "example": false
                    },
                    "code": {
                      "type": "string",
                      "example": "COMMON000"
                    },
                    "message": {
                      "type": "string",
                      "example": "서버 에러, 관리자에게 문의 바랍니다."
                    },
                    "result": {}
                  },
                  "xml": {
                    "name": "main"
                  }
                }
              },
              "application/xml": {
                "schema": {
                  "type": "object",
                  "properties": {
                    "isSuccess": {
                      "type": "boolean",
                      "example": false
                    },
                    "code": {
                      "type": "string",
                      "example": "COMMON000"
                    },
                    "message": {
                      "type": "string",
                      "example": "서버 에러, 관리자에게 문의 바랍니다."
                    },
                    "result": {}
                  },
                  "xml": {
                    "name": "main"
                  }
                }
              }
            }
          }
        },
        "security": [
          {
            "BearerAuth": []
          }
        ],
        "requestBody": {
          "description": "참가할 진형",
          "required": true,
          "content": {
            "application/json": {
              "schema": {
                "type": "object",
                "properties": {
                  "side": {
                    "type": "string",
                    "enum": [
                      "A",
                      "B",
                      "P"
                    ],
                    "example": "A"
                  }
                },
                "required": [
                  "side"
                ]
              }
            }
          }
        }
      }
    },
    "/battle/rooms/{roomId}/start": {
      "post": {
        "tags": [
          "BattleRoom"
        ],
        "summary": "배틀 시작 API",
        "description": "",
        "parameters": [
          {
            "name": "roomId",
            "in": "path",
            "required": true,
            "schema": {
              "type": "string"
            },
            "description": "배틀방 ID",
            "format": "int64",
            "example": 1
          }
        ],
        "responses": {
          "200": {
            "description": "시작 성공",
            "content": {
              "application/json": {
                "schema": {
                  "type": "object",
                  "properties": {
                    "isSuccess": {
                      "type": "boolean",
                      "example": true
                    },
                    "code": {
                      "type": "string",
                      "example": "200"
                    },
                    "message": {
                      "type": "string",
                      "example": "success!"
                    },
                    "result": {
                      "type": "object",
                      "properties": {
                        "roomId": {
                          "type": "number",
                          "example": 1
                        },
                        "status": {
                          "type": "string",
                          "example": "PLAYING"
                        },
                        "startedAt": {
                          "type": "string",
                          "example": "2025-05-25T12:34:56.000Z"
                        }
                      }
                    }
                  },
                  "xml": {
                    "name": "main"
                  }
                }
              },
              "application/xml": {
                "schema": {
                  "type": "object",
                  "properties": {
                    "isSuccess": {
                      "type": "boolean",
                      "example": true
                    },
                    "code": {
                      "type": "string",
                      "example": "200"
                    },
                    "message": {
                      "type": "string",
                      "example": "success!"
                    },
                    "result": {
                      "type": "object",
                      "properties": {
                        "roomId": {
                          "type": "number",
                          "example": 1
                        },
                        "status": {
                          "type": "string",
                          "example": "PLAYING"
                        },
                        "startedAt": {
                          "type": "string",
                          "example": "2025-05-25T12:34:56.000Z"
                        }
                      }
                    }
                  },
                  "xml": {
                    "name": "main"
                  }
                }
              }
            }
          },
          "400": {
            "description": "잘못된 요청 (INVALID_STATE 등)",
            "content": {
              "application/json": {
                "schema": {
                  "type": "object",
                  "properties": {
                    "isSuccess": {
                      "type": "boolean",
                      "example": false
                    },
                    "code": {
                      "type": "string",
                      "example": "COMMON001"
                    },
                    "message": {
                      "type": "string",
                      "example": "잘못된 요청입니다."
                    },
                    "result": {}
                  },
                  "xml": {
                    "name": "main"
                  }
                }
              },
              "application/xml": {
                "schema": {
                  "type": "object",
                  "properties": {
                    "isSuccess": {
                      "type": "boolean",
                      "example": false
                    },
                    "code": {
                      "type": "string",
                      "example": "COMMON001"
                    },
                    "message": {
                      "type": "string",
                      "example": "잘못된 요청입니다."
                    },
                    "result": {}
                  },
                  "xml": {
                    "name": "main"
                  }
                }
              }
            }
          },
          "401": {
            "description": "토큰 오류",
            "content": {
              "application/json": {
                "schema": {
                  "type": "object",
                  "properties": {
                    "isSuccess": {
                      "type": "boolean",
                      "example": false
                    },
                    "code": {
                      "type": "string",
                      "example": "MEMBER4006"
                    },
                    "message": {
                      "type": "string",
                      "example": "토큰의 형식이 올바르지 않습니다. 다시 확인해주세요."
                    },
                    "result": {}
                  },
                  "xml": {
                    "name": "main"
                  }
                }
              },
              "application/xml": {
                "schema": {
                  "type": "object",
                  "properties": {
                    "isSuccess": {
                      "type": "boolean",
                      "example": false
                    },
                    "code": {
                      "type": "string",
                      "example": "MEMBER4006"
                    },
                    "message": {
                      "type": "string",
                      "example": "토큰의 형식이 올바르지 않습니다. 다시 확인해주세요."
                    },
                    "result": {}
                  },
                  "xml": {
                    "name": "main"
                  }
                }
              }
            }
          },
          "403": {
            "description": "권한 없음 (방장만 시작 가능)",
            "content": {
              "application/json": {
                "schema": {
                  "type": "object",
                  "properties": {
                    "isSuccess": {
                      "type": "boolean",
                      "example": false
                    },
                    "code": {
                      "type": "string",
                      "example": "COMMON004"
                    },
                    "message": {
                      "type": "string",
                      "example": "금지된 요청입니다."
                    },
                    "result": {}
                  },
                  "xml": {
                    "name": "main"
                  }
                }
              },
              "application/xml": {
                "schema": {
                  "type": "object",
                  "properties": {
                    "isSuccess": {
                      "type": "boolean",
                      "example": false
                    },
                    "code": {
                      "type": "string",
                      "example": "COMMON004"
                    },
                    "message": {
                      "type": "string",
                      "example": "금지된 요청입니다."
                    },
                    "result": {}
                  },
                  "xml": {
                    "name": "main"
                  }
                }
              }
            }
          },
          "404": {
            "description": "방을 찾을 수 없음",
            "content": {
              "application/json": {
                "schema": {
                  "type": "object",
                  "properties": {
                    "isSuccess": {
                      "type": "boolean",
                      "example": false
                    },
                    "code": {
                      "type": "string",
                      "example": "ROOMIN4005"
                    },
                    "message": {
                      "type": "string",
                      "example": "방을 찾을 수가 없습니다."
                    },
                    "result": {}
                  },
                  "xml": {
                    "name": "main"
                  }
                }
              },
              "application/xml": {
                "schema": {
                  "type": "object",
                  "properties": {
                    "isSuccess": {
                      "type": "boolean",
                      "example": false
                    },
                    "code": {
                      "type": "string",
                      "example": "ROOMIN4005"
                    },
                    "message": {
                      "type": "string",
                      "example": "방을 찾을 수가 없습니다."
                    },
                    "result": {}
                  },
                  "xml": {
                    "name": "main"
                  }
                }
              }
            }
          },
          "500": {
            "description": "서버 내부 오류",
            "content": {
              "application/json": {
                "schema": {
                  "type": "object",
                  "properties": {
                    "isSuccess": {
                      "type": "boolean",
                      "example": false
                    },
                    "code": {
                      "type": "string",
                      "example": "COMMON000"
                    },
                    "message": {
                      "type": "string",
                      "example": "서버 에러, 관리자에게 문의 바랍니다."
                    },
                    "result": {}
                  },
                  "xml": {
                    "name": "main"
                  }
                }
              },
              "application/xml": {
                "schema": {
                  "type": "object",
                  "properties": {
                    "isSuccess": {
                      "type": "boolean",
                      "example": false
                    },
                    "code": {
                      "type": "string",
                      "example": "COMMON000"
                    },
                    "message": {
                      "type": "string",
                      "example": "서버 에러, 관리자에게 문의 바랍니다."
                    },
                    "result": {}
                  },
                  "xml": {
                    "name": "main"
                  }
                }
              }
            }
          }
        },
        "security": [
          {
            "BearerAuth": []
          }
        ]
      }
    },
    "/quests/{id}": {
      "get": {
        "tags": [
          "Quest"
        ],
        "summary": "퀘스트 ID로 단일 퀘스트 조회 API",
        "description": "",
        "parameters": [
          {
            "name": "id",
            "in": "path",
            "required": true,
            "schema": {
              "type": "string"
            },
            "description": "조회할 퀘스트의 ID",
            "example": 1
          }
        ],
        "responses": {
          "200": {
            "description": "퀘스트 조회 성공",
            "content": {
              "application/json": {
                "schema": {
                  "type": "object",
                  "properties": {
                    "isSuccess": {
                      "type": "boolean",
                      "example": true
                    },
                    "code": {
                      "type": "number",
                      "example": 200
                    },
                    "message": {
                      "type": "string",
                      "example": "성공"
                    },
                    "result": {
                      "type": "object",
                      "example": {
                        "id": 1,
                        "name": "첫번째 퀘스트",
                        "description": "퀘스트 상세 설명",
                        "type": "daily",
                        "rewardPts": 100,
                        "createdAt": "2025-05-31T00:00:00.000Z"
                      }
                    }
                  }
                }
              }
            }
          },
          "400": {
            "description": "잘못된 퀘스트 ID",
            "content": {
              "application/json": {
                "schema": {
                  "isSuccess": {
                    "type": "boolean",
                    "example": false
                  },
                  "code": {
                    "type": "number",
                    "example": 400
                  },
                  "message": {
                    "type": "string",
                    "example": "퀘스트 ID가 올바르지 않습니다."
                  },
                  "result": {
                    "type": "object",
                    "nullable": true,
                    "example": null
                  }
                }
              }
            }
          },
          "401": {
            "description": "토큰 형식 오류",
            "content": {
              "application/json": {
                "schema": {
                  "isSuccess": {
                    "type": "boolean",
                    "example": false
                  },
                  "code": {
                    "type": "string",
                    "example": "TOKEN_FORMAT_INCORRECT"
                  },
                  "message": {
                    "type": "string",
                    "example": "토큰 형식이 올바르지 않습니다."
                  },
                  "result": {
                    "type": "object",
                    "nullable": true,
                    "example": null
                  }
                }
              }
            }
          },
          "403": {
            "description": "Forbidden"
          },
          "404": {
            "description": "퀘스트를 찾을 수 없음",
            "content": {
              "application/json": {
                "schema": {
                  "isSuccess": {
                    "type": "boolean",
                    "example": false
                  },
                  "code": {
                    "type": "number",
                    "example": 404
                  },
                  "message": {
                    "type": "string",
                    "example": "퀘스트를 찾을 수 없습니다."
                  },
                  "result": {
                    "type": "object",
                    "nullable": true,
                    "example": null
                  }
                }
              }
            }
          },
          "500": {
            "description": "서버 오류",
            "content": {
              "application/json": {
                "schema": {
                  "isSuccess": {
                    "type": "boolean",
                    "example": false
                  },
                  "code": {
                    "type": "string",
                    "example": "SERVER_ERROR"
                  },
                  "message": {
                    "type": "string",
                    "example": "서버 오류 발생"
                  },
                  "result": {
                    "type": "object",
                    "nullable": true,
                    "example": null
                  }
                }
              }
            }
          }
        },
        "security": [
          {
            "BearerAuth": []
          }
        ]
      }
    },
    "/quests/status/{userId}/{questId}": {
      "post": {
        "tags": [
          "Quest"
        ],
        "summary": "퀘스트 완료 처리 API",
        "description": "",
        "parameters": [
          {
            "name": "userId",
            "in": "path",
            "required": true,
            "schema": {
              "type": "string"
            },
            "description": "유저 ID",
            "format": "int64",
            "example": 1
          },
          {
            "name": "questId",
            "in": "path",
            "required": true,
            "schema": {
              "type": "string"
            },
            "description": "퀘스트 ID",
            "format": "int64",
            "example": 2
          }
        ],
        "responses": {
          "200": {
            "description": "퀘스트 완료 성공",
            "content": {
              "application/json": {
                "schema": {
                  "type": "object",
                  "properties": {
                    "isSuccess": {
                      "type": "boolean",
                      "example": true
                    },
                    "code": {
                      "type": "number",
                      "example": 200
                    },
                    "message": {
                      "type": "string",
                      "example": "퀘스트 완료 성공"
                    },
                    "result": {
                      "type": "object",
                      "properties": {
                        "questId": {
                          "type": "number",
                          "example": 2
                        },
                        "isCompleted": {
                          "type": "boolean",
                          "example": true
                        }
                      }
                    }
                  }
                }
              }
            }
          },
          "400": {
            "description": "잘못된 요청",
            "content": {
              "application/json": {
                "schema": {
                  "type": "object",
                  "properties": {
                    "isSuccess": {
                      "type": "boolean",
                      "example": false
                    },
                    "code": {
                      "type": "string",
                      "example": "BAD_REQUEST"
                    },
                    "message": {
                      "type": "string",
                      "example": "필수 파라미터가 누락되었습니다."
                    },
                    "result": {
                      "type": "object",
                      "nullable": true,
                      "example": null
                    }
                  }
                }
              }
            }
          },
          "401": {
            "description": "Unauthorized"
          },
          "403": {
            "description": "Forbidden"
          },
          "500": {
            "description": "서버 오류",
            "content": {
              "application/json": {
                "schema": {
                  "type": "object",
                  "properties": {
                    "isSuccess": {
                      "type": "boolean",
                      "example": false
                    },
                    "code": {
                      "type": "string",
                      "example": "SERVER_ERROR"
                    },
                    "message": {
                      "type": "string",
                      "example": "서버 오류가 발생했습니다."
                    },
                    "result": {
                      "type": "object",
                      "nullable": true,
                      "example": null
                    }
                  }
                }
              }
            }
          }
        },
        "security": [
          {
            "BearerAuth": []
          }
        ],
        "requestBody": {
          "content": {
            "application/json": {
              "schema": {
                "type": "object",
                "properties": {
                  "description": {
                    "example": "any"
                  },
                  "content": {
                    "example": "any"
                  },
                  "code": {
                    "example": "any"
                  },
                  "message": {
                    "example": "any"
                  },
                  "result": {
                    "example": "any"
                  },
                  "isCompleted": {
                    "example": "any"
                  }
                }
              }
            }
          }
        }
      }
    },
    "/quests/reward/{userId}/{questId}": {
      "post": {
        "tags": [
          "Quest"
        ],
        "summary": "퀘스트 보상 수령 API",
        "description": "",
        "parameters": [
          {
            "name": "userId",
            "in": "path",
            "required": true,
            "schema": {
              "type": "string"
            }
          },
          {
            "name": "questId",
            "in": "path",
            "required": true,
            "schema": {
              "type": "string"
            }
          }
        ],
        "responses": {
          "200": {
            "description": "보상 수령 성공",
            "content": {
              "application/json": {
                "schema": {
                  "type": "object",
                  "properties": {
                    "isSuccess": {
                      "type": "boolean",
                      "example": true
                    },
                    "code": {
                      "type": "number",
                      "example": 200
                    },
                    "message": {
                      "type": "string",
                      "example": "보상을 성공적으로 받았습니다."
                    },
                    "result": {
                      "type": "object",
                      "example": {
                        "reward": 100
                      }
                    }
                  }
                }
              }
            }
          },
          "400": {
            "description": "Bad Request"
          },
          "401": {
            "description": "Unauthorized"
          },
          "403": {
            "description": "Forbidden"
          },
          "500": {
            "description": "Internal Server Error"
          }
        },
        "security": [
          {
            "BearerAuth": []
          }
        ],
        "requestBody": {
          "content": {
            "application/json": {
              "schema": {
                "type": "object",
                "properties": {
                  "in": {
                    "example": "any"
                  },
                  "description": {
                    "example": "any"
                  },
                  "required": {
                    "example": "any"
                  },
                  "schema": {
                    "example": "any"
                  },
                  "questId": {
                    "example": "any"
                  },
                  "code": {
                    "example": "any"
                  },
                  "message": {
                    "example": "any"
                  },
                  "result": {
                    "example": "any"
                  }
                }
              }
            }
          }
        }
      }
    },
    "/quests/reset-daily": {
      "post": {
        "tags": [
          "Quest"
        ],
        "summary": "일일 퀘스트 초기화 API",
        "description": "매일 자정마다 모든 사용자의 퀘스트 완료 및 보상 상태를 초기화합니다.",
        "responses": {
          "200": {
            "description": "일일 퀘스트 초기화 성공",
            "content": {
              "application/json": {
                "schema": {
                  "type": "object",
                  "properties": {
                    "isSuccess": {
                      "type": "boolean",
                      "example": true
                    },
                    "code": {
                      "type": "number",
                      "example": 200
                    },
                    "message": {
                      "type": "string",
                      "example": "일일 퀘스트가 초기화되었습니다."
                    },
                    "result": {
                      "type": "object",
                      "nullable": true,
                      "example": null
                    }
                  }
                }
              }
            }
          },
          "401": {
            "description": "Unauthorized"
          },
          "403": {
            "description": "Forbidden"
          },
          "500": {
            "description": "서버 오류로 초기화 실패",
            "content": {
              "application/json": {
                "schema": {
                  "type": "object",
                  "properties": {
                    "isSuccess": {
                      "type": "boolean",
                      "example": false
                    },
                    "code": {
                      "type": "number",
                      "example": 500
                    },
                    "message": {
                      "type": "string",
                      "example": "서버 오류로 퀘스트 초기화에 실패했습니다."
                    },
                    "result": {
                      "type": "object",
                      "nullable": true,
                      "example": null
                    }
                  }
                }
              }
            }
          }
        }
      }
    }
  },
  "components": {
    "securitySchemes": {
      "BearerAuth": {
        "type": "http",
        "scheme": "bearer",
        "bearerFormat": "JWT"
      }
    }
  },
  "security": [
    {
      "BearerAuth": []
    }
  ]
}